Metadata-Version: 1.0
Name: imagepro
Version: 0.0.3
Summary: Image Processing for Smart Seller
Home-page: UNKNOWN
Author: Jason Xing Zhang
Author-email: jason.xing.zhang@gmail.com
License: MIT License
Platform: any
